cellvit_light/__init__.py
cellvit_light/base_ml/__init__.py
cellvit_light/base_ml/base_cli.py
cellvit_light/base_ml/base_early_stopping.py
cellvit_light/base_ml/base_experiment.py
cellvit_light/base_ml/base_loss.py
cellvit_light/base_ml/base_optim.py
cellvit_light/base_ml/base_trainer.py
cellvit_light/base_ml/base_utils.py
cellvit_light/base_ml/base_validator.py
cellvit_light/cell_segmentation/__init__.py
cellvit_light/cell_segmentation/run_cellvit.py
cellvit_light/cell_segmentation/run_cpp_net.py
cellvit_light/cell_segmentation/run_stardist.py
cellvit_light/cell_segmentation/datasets/base_cell.py
cellvit_light/cell_segmentation/datasets/cell_graph_datamodel.py
cellvit_light/cell_segmentation/datasets/conic.py
cellvit_light/cell_segmentation/datasets/consep.py
cellvit_light/cell_segmentation/datasets/dataset_coordinator.py
cellvit_light/cell_segmentation/datasets/monuseg.py
cellvit_light/cell_segmentation/datasets/pannuke.py
cellvit_light/cell_segmentation/datasets/prepare_monuseg.py
cellvit_light/cell_segmentation/datasets/prepare_pannuke.py
cellvit_light/cell_segmentation/inference/__init__.py
cellvit_light/cell_segmentation/inference/cell_detection.py
cellvit_light/cell_segmentation/trainer/__init__.py
cellvit_light/cell_segmentation/trainer/trainer_cellvit.py
cellvit_light/cell_segmentation/trainer/trainer_cpp_net.py
cellvit_light/cell_segmentation/trainer/trainer_stardist.py
cellvit_light/cell_segmentation/utils/__init__.py
cellvit_light/cell_segmentation/utils/metrics.py
cellvit_light/cell_segmentation/utils/post_proc_cellvit.py
cellvit_light/cell_segmentation/utils/post_proc_stardist.py
cellvit_light/cell_segmentation/utils/template_geojson.py
cellvit_light/cell_segmentation/utils/tools.py
cellvit_light/configs/__init__.py
cellvit_light/configs/python/__init__.py
cellvit_light/configs/python/config.py
cellvit_light/datamodel/__init__.py
cellvit_light/datamodel/graph_datamodel.py
cellvit_light/datamodel/wsi_datamodel.py
cellvit_light/models/__init__.py
cellvit_light-0.0.5.dist-info/LICENSE
cellvit_light-0.0.5.dist-info/METADATA
cellvit_light-0.0.5.dist-info/WHEEL
cellvit_light-0.0.5.dist-info/top_level.txt
cellvit_light-0.0.5.dist-info/RECORD
