Metadata-Version: 2.1
Name: cellvit_light
Version: 0.0.5
Requires-Python: >=3.9
License-File: LICENSE
Requires-Dist: pydantic ==1.10.4
Requires-Dist: geojson
Requires-Dist: rasterio
Requires-Dist: ujson
Requires-Dist: pandarallel
